MANIFEST.in
setup.py
recipy/PatchBaseScientific.py
recipy/PatchImporter.py
recipy/PatchScientific.py
recipy/PatchSimple.py
recipy/PatchWarnings.py
recipy/__init__.py
recipy/__main__.py
recipy/log.py
recipy/utils.py
recipy.egg-info/PKG-INFO
recipy.egg-info/SOURCES.txt
recipy.egg-info/dependency_links.txt
recipy.egg-info/entry_points.txt
recipy.egg-info/requires.txt
recipy.egg-info/top_level.txt
recipyCmd/__init__.py
recipyCmd/recipycmd.py
recipyCommon/__init__.py
recipyCommon/config.py
recipyCommon/libraryversions.py
recipyCommon/tinydb_utils.py
recipyCommon/utils.py
recipyCommon/version_control.py
recipyGui/__init__.py
recipyGui/forms.py
recipyGui/views.py
recipyGui/static/css/main.css
recipyGui/templates/base.html
recipyGui/templates/details.html
recipyGui/templates/list.html
recipyGui/templates/macros.html
recipyGui/templates/patched_modules.html
recipyGui/tests/__init__.py
recipyGui/tests/test_filters.py
recipyGui/tests/test_recipyGui.py
test/test_config.py
test/test_libraryversions.py
test/test_tinydb_utils.py
test/test_utils.py