Metadata-Version: 1.1
Name: recipy
Version: 0.3.0
Summary: A frictionless provenance framework for Python
Home-page: https://github.com/recipy/recipy
Author: Robin Wilson, Raquel Alegre, Janneke van der Zwaan
Author-email: robin@rtwilson.com
License: Apache
Keywords: development,science,reproducibility,provenance
Platform: UNKNOWN
Classifier: Development Status :: 3 - Alpha
Classifier: Intended Audience :: Developers
Classifier: License :: OSI Approved :: Apache Software License
Classifier: Programming Language :: Python :: 2
Classifier: Programming Language :: Python :: 2.6
Classifier: Programming Language :: Python :: 2.7
Classifier: Programming Language :: Python :: 3
Classifier: Programming Language :: Python :: 3.2
Classifier: Programming Language :: Python :: 3.3
Classifier: Programming Language :: Python :: 3.4
